{
  "unversionedId": "lenguajes/go",
  "id": "lenguajes/go",
  "title": "Go!",
  "description": "Docusaurus can manage multiple versions of your docs.",
  "source": "@site/docs/lenguajes/go.md",
  "sourceDirName": "lenguajes",
  "slug": "/lenguajes/go",
  "permalink": "/docs/lenguajes/go",
  "editUrl": "https://github.com/facebook/docusaurus/tree/main/packages/create-docusaurus/templates/shared/docs/lenguajes/go.md",
  "tags": [],
  "version": "current",
  "sidebarPosition": 3,
  "frontMatter": {
    "sidebar_position": 3
  },
  "sidebar": "tutorialSidebar",
  "previous": {
    "title": "Flutter",
    "permalink": "/docs/lenguajes/flutter"
  },
  "next": {
    "title": "JS",
    "permalink": "/docs/lenguajes/js"
  }
}