{
  "/docs/markdown-page-dbb": {
    "component": "1f391b9e",
    "content": "393be207"
  },
  "/docs/-bc7": {
    "component": "1be78505",
    "versionMetadata": "935f2afb"
  },
  "/docs/-2bf": {
    "component": "17896441",
    "content": "0e384e19"
  },
  "/docs/aws/cloud-developer-8cd": {
    "component": "17896441",
    "content": "7d7f4a65"
  },
  "/docs/aws/cloud-practitioner-cc5": {
    "component": "17896441",
    "content": "82ba38e7"
  },
  "/docs/db/data-architect-506": {
    "component": "17896441",
    "content": "0dbe42e4"
  },
  "/docs/db/data-lakes-d8b": {
    "component": "17896441",
    "content": "19b60714"
  },
  "/docs/db/data-warehouse-565": {
    "component": "17896441",
    "content": "8ab7ba2e"
  },
  "/docs/db/databases-a7c": {
    "component": "17896441",
    "content": "2da08125"
  },
  "/docs/db/sql-92b": {
    "component": "17896441",
    "content": "d1d8bf81"
  },
  "/docs/gcp/cloud-digital-leader-c63": {
    "component": "17896441",
    "content": "70fc0e36"
  },
  "/docs/gcp/cloud-engineer-b5e": {
    "component": "17896441",
    "content": "e4baeaad"
  },
  "/docs/herramientas/DDD-ace": {
    "component": "17896441",
    "content": "3cf2454c"
  },
  "/docs/herramientas/docker-cfc": {
    "component": "17896441",
    "content": "ba19754b"
  },
  "/docs/herramientas/git-88e": {
    "component": "17896441",
    "content": "278e2c57"
  },
  "/docs/herramientas/jira-4ba": {
    "component": "17896441",
    "content": "8768d58c"
  },
  "/docs/herramientas/kubernetes-02a": {
    "component": "17896441",
    "content": "29fb3d08"
  },
  "/docs/herramientas/terraform-18d": {
    "component": "17896441",
    "content": "e44bfa99"
  },
  "/docs/herramientas/ux-4e4": {
    "component": "17896441",
    "content": "36a4d00d"
  },
  "/docs/lenguajes/dart-f3c": {
    "component": "17896441",
    "content": "f3099cf9"
  },
  "/docs/lenguajes/flutter-c55": {
    "component": "17896441",
    "content": "a81ac293"
  },
  "/docs/lenguajes/go-0de": {
    "component": "17896441",
    "content": "382caf3c"
  },
  "/docs/lenguajes/js-c27": {
    "component": "17896441",
    "content": "c82e37c7"
  }
}